[
	{
		"idOrder": 2844597,
		"isBuyer": false,
		"seller": {
			"idUser": 9999,
			"username": "Maxi",
			"country": "D",
			"isCommercial": 1,
			"riskGroup": 0,
			"reputation": 1,
			"shipsFast": 1,
			"sellCount": 254,
			"onVacation": false,
			"idDisplayLanguage": 3,
			"name": {
				"firstName": "Maximilian",
				"lastName": "Mustermann"
			},
			"address": {
				"name": "Maximilian Mustermann",
				"extra": "c/o Musterfrau",
				"street": "Hauptweg 15",
				"zip": "12345",
				"city": "Berlin",
				"country": "D"
			}
		},
		"buyer": {
			"idUser": 9998,
			"username": "Mini",
			"country": "IT",
			"isCommercial": 0,
			"riskGroup": 0,
			"reputation": 0,
			"shipsFast": 0,
			"sellCount": 0,
			"onVacation": false,
			"idDisplayLanguage": 5,
			"name": {
				"firstName": "Mario",
				"lastName": "Rossi"
			},
			"address": {
				"name": "Mario Rossi",
				"extra": "",
				"street": "46 de Gasperi",
				"zip": "10000",
				"city": "Roma",
				"country": "IT"
			}
		},
		"state": {
			"state": "evaluated",
			"dateBought": "2023-01.03T23:47:24+0100",
			"datePaid": "2013-12.03T23:47:24+0100",
			"dateSent": "2013-11-22.02:03:42+0100",
			"dateReceived": "2013-11-26T14:22:30+0100"
		},
		"shippingMethod": {
			"idShippingMethod": 20,
			"name": "Standardbrief International",
			"price": 1,
			"isLetter": false,
			"isInsured": false
		},
		"trackingNumber": "",
		"temporaryEmail": "",
		"isPresale": false,
		"shippingAddress": {
			"name": "Mario Rossi",
			"extra": "",
			"street": "46 de Gasperi",
			"zip": "10000",
			"city": "Roma",
			"country": "IT"
		},
		"articleCount": 2,
		"evaluation": {
			"evaluationGrade": 1,
			"itemDescription": 4,
			"packaging": 1,
			"speed": 1,
			"comment": "not foil, but alternate art and wrong edition",
			"complaint": [
				"wrongEd"
			]
		},
		"article": [
			{
				"idArticle": 122973759,
				"idProduct": 258590,
				"language": {
					"idLanguage": 1,
					"languageName": "English"
				},
				"comments": "",
				"price": 4.9,
				"count": 2,
				"product": {
					"name": "Despair of Winter",
					"image": ".\/img\/items\/3\/War_of_the_Ancients\/despair_of_winter.jpg",
					"expansion": "La Guerra de los Hermanos",
					"expIcon": 204,
					"rarity": "Rare"
				},
				"condition": "NM",
				"isFoil": true,
				"isSigned": false,
				"isPlayset": false
			}
		],
		"articleValue": 9.8,
		"totalValue": 10.8,
		"idCurrency": 1,
		"currencyCode": "EUR",
		"phoneNumber": 123412345678
	},
	{
		"idOrder": 2844598,
		"isBuyer": false,
		"seller": {
			"idUser": 9999,
			"username": "Maxi",
			"country": "D",
			"isCommercial": 1,
			"riskGroup": 0,
			"reputation": 1,
			"shipsFast": 1,
			"sellCount": 254,
			"onVacation": false,
			"idDisplayLanguage": 3,
			"name": {
				"firstName": "Maximilian",
				"lastName": "Mustermann"
			},
			"address": {
				"name": "Maximilian Mustermann",
				"extra": "c/o Musterfrau",
				"street": "Hauptweg 15",
				"zip": "12345",
				"city": "Berlin",
				"country": "D"
			}
		},
		"buyer": {
			"idUser": 9998,
			"username": "Mini",
			"country": "IT",
			"isCommercial": 0,
			"riskGroup": 0,
			"reputation": 0,
			"shipsFast": 0,
			"sellCount": 0,
			"onVacation": false,
			"idDisplayLanguage": 5,
			"name": {
				"firstName": "Mario",
				"lastName": "Rossi"
			},
			"address": {
				"name": "Mario Rossi",
				"extra": "",
				"street": "46 de Gasperi",
				"zip": "10000",
				"city": "Roma",
				"country": "IT"
			}
		},
		"state": {
			"state": "shipped",
			"dateBought": "2014-01.02T23:47:24+0100",
			"datePaid": "2014-01.02T23:47:24+0100",
			"dateSent": "2014-01.02T23:47:24+0100",
			"dateReceived": "2014-01.02T23:47:24+0100"
		},
		"shippingMethod": {
			"idShippingMethod": 20,
			"name": "Standardbrief International",
			"price": 1,
			"isLetter": false,
			"isInsured": false
		},
		"trackingNumber": "",
		"temporaryEmail": "",
		"isPresale": false,
		"shippingAddress": {
			"name": "Mario Rossi",
			"extra": "",
			"street": "46 de Gasperi",
			"zip": "10000",
			"city": "Roma",
			"country": "IT"
		},
		"articleCount": 2,
		"evaluation": {
			"evaluationGrade": 1,
			"itemDescription": 4,
			"packaging": 1,
			"speed": 1,
			"comment": "not foil, but alternate art and wrong edition",
			"complaint": [
				"wrongEd"
			]
		},
		"article": [
			{
				"idArticle": 122973759,
				"idProduct": 258590,
				"language": {
					"idLanguage": 1,
					"languageName": "English"
				},
				"comments": "",
				"price": 6.9,
				"count": 2,
				"product": {
					"name": "Deificacion",
					"image": ".\/img\/items\/3\/War_of_the_Ancients\/despair_of_winter.jpg",
					"expansion": "La Guerra de los Hermanos",
					"expIcon": 204,
					"rarity": "Rare"
				},
				"condition": "NM",
				"isFoil": true,
				"isSigned": false,
				"isPlayset": false
			},
			{
				"idArticle": 122973759,
				"idProduct": 258590,
				"language": {
					"idLanguage": 1,
					"languageName": "English"
				},
				"comments": "",
				"price": 16.9,
				"count": 2,
				"product": {
					"name": "Ruptura de la chispa",
					"image": ".\/img\/items\/3\/War_of_the_Ancients\/despair_of_winter.jpg",
					"expansion": "La Guerra de los Hermanos",
					"expIcon": 204,
					"rarity": "Rare"
				},
				"condition": "NM",
				"isFoil": true,
				"isSigned": false,
				"isPlayset": false
			},
			{
				"idArticle": 122973759,
				"idProduct": 258590,
				"language": {
					"idLanguage": 1,
					"languageName": "English"
				},
				"comments": "",
				"price": 2.9,
				"count": 2,
				"product": {
					"name": "Filtrar",
					"image": ".\/img\/items\/3\/War_of_the_Ancients\/despair_of_winter.jpg",
					"expansion": "La Guerra de los Hermanos",
					"expIcon": 204,
					"rarity": "Rare"
				},
				"condition": "NM",
				"isFoil": true,
				"isSigned": false,
				"isPlayset": false
			}
		],
		"articleValue": 9.8,
		"totalValue": 53.4,
		"idCurrency": 1,
		"currencyCode": "EUR",
		"phoneNumber": 123412345678
	},
	{
		"idOrder": 2844599,
		"isBuyer": false,
		"seller": {
			"idUser": 9999,
			"username": "Maxi",
			"country": "D",
			"isCommercial": 1,
			"riskGroup": 0,
			"reputation": 1,
			"shipsFast": 1,
			"sellCount": 254,
			"onVacation": false,
			"idDisplayLanguage": 3,
			"name": {
				"firstName": "Maximilian",
				"lastName": "Mustermann"
			},
			"address": {
				"name": "Maximilian Mustermann",
				"extra": "c/o Musterfrau",
				"street": "Hauptweg 15",
				"zip": "12345",
				"city": "Berlin",
				"country": "D"
			}
		},
		"buyer": {
			"idUser": 9998,
			"username": "Mini",
			"country": "IT",
			"isCommercial": 0,
			"riskGroup": 0,
			"reputation": 0,
			"shipsFast": 0,
			"sellCount": 0,
			"onVacation": false,
			"idDisplayLanguage": 5,
			"name": {
				"firstName": "Mario",
				"lastName": "Rossi"
			},
			"address": {
				"name": "Mario Rossi",
				"extra": "",
				"street": "46 de Gasperi",
				"zip": "10000",
				"city": "Roma",
				"country": "IT"
			}
		},
		"state": {
			"state": "paid",
			"dateBought": "2014-02.02T23:47:24+0100",
			"datePaid": "2014-02.02T23:47:24+0100",
			"dateSent": "",
			"dateReceived": "2014-02.02T23:47:24+0100"
		},
		"shippingMethod": {
			"idShippingMethod": 20,
			"name": "Standardbrief International",
			"price": 1,
			"isLetter": false,
			"isInsured": false
		},
		"trackingNumber": "",
		"temporaryEmail": "",
		"isPresale": false,
		"shippingAddress": {
			"name": "Mario Rossi",
			"extra": "",
			"street": "46 de Gasperi",
			"zip": "10000",
			"city": "Roma",
			"country": "IT"
		},
		"articleCount": 2,
		"evaluation": {
			"evaluationGrade": 1,
			"itemDescription": 4,
			"packaging": 1,
			"speed": 1,
			"comment": "not foil, but alternate art and wrong edition",
			"complaint": [
				"wrongEd"
			]
		},
		"article": [
			{
				"idArticle": 122973759,
				"idProduct": 258590,
				"language": {
					"idLanguage": 1,
					"languageName": "English"
				},
				"comments": "",
				"price": 8,
				"count": 1,
				"product": {
					"name": "Peak Personage Stealth Rogue, Shojodoji",
					"image": ".\/img\/items\/3\/War_of_the_Ancients\/despair_of_winter.jpg",
					"expansion": "D Booster Set 08: Minerva Rising",
					"expIcon": 204,
					"rarity": "RRR"
				},
				"condition": "NM",
				"isFoil": true,
				"isSigned": false,
				"isPlayset": false
			},
			{
				"idArticle": 122973759,
				"idProduct": 258590,
				"language": {
					"idLanguage": 1,
					"languageName": "English"
				},
				"comments": "",
				"price": 7,
				"count": 3,
				"product": {
					"name": "Silver Thorn Dragon Tamer, Luquier",
					"image": ".\/img\/items\/3\/War_of_the_Ancients\/despair_of_winter.jpg",
					"expansion": "D Booster Set 08: Minerva Rising",
					"expIcon": 204,
					"rarity": "RRR"
				},
				"condition": "NM",
				"isFoil": true,
				"isSigned": false,
				"isPlayset": false
			}
		],
		"articleValue": 9.8,
		"totalValue": 29,
		"idCurrency": 1,
		"currencyCode": "EUR",
		"phoneNumber": 123412345678
	}
]